CHANGES.txt
COPYRIGHT.txt
LICENSE.txt
README.txt
TODO.txt
bootstrap.py
buildout.cfg
setup.py
src/z3c/__init__.py
src/z3c.securitytool.egg-info/PKG-INFO
src/z3c.securitytool.egg-info/SOURCES.txt
src/z3c.securitytool.egg-info/dependency_links.txt
src/z3c.securitytool.egg-info/namespace_packages.txt
src/z3c.securitytool.egg-info/not-zip-safe
src/z3c.securitytool.egg-info/requires.txt
src/z3c.securitytool.egg-info/top_level.txt
src/z3c/securitytool/README.txt
src/z3c/securitytool/SETUP.cfg
src/z3c/securitytool/__init__.py
src/z3c/securitytool/concordTimesDummyViews.zcml
src/z3c/securitytool/concordTimesPrincipals.zcml
src/z3c/securitytool/configure.zcml
src/z3c/securitytool/demoSetup.py
src/z3c/securitytool/dummy.pt
src/z3c/securitytool/ftesting.zcml
src/z3c/securitytool/globalfunctions.py
src/z3c/securitytool/interfaces.py
src/z3c/securitytool/matrixdetails.py
src/z3c/securitytool/permissiondetails.py
src/z3c/securitytool/principaldetails.py
src/z3c/securitytool/securitytool.py
src/z3c/securitytool/site.zcml
src/z3c/securitytool/testing.py
src/z3c/securitytool/tests.py
src/z3c/securitytool/z3c.securitytool-configure.zcml
src/z3c/securitytool/browser/__init__.py
src/z3c/securitytool/browser/configure.zcml
src/z3c/securitytool/browser/permdetails.pt
src/z3c/securitytool/browser/principalinfo.pt
src/z3c/securitytool/browser/securitytool.css
src/z3c/securitytool/browser/viewprincipalmatrix.pt
src/z3c/securitytool/browser/views.py