Metadata-Version: 1.0
Name: z3c.securitytool
Version: 0.5.0
Summary: A security audit tool and demo for Zope3 views
Home-page: UNKNOWN
Author: Daniel Blackburn, Stephan Richter, Randy Crafton
Author-email: zope-dev@zope.org
License: ZPL 2.1
Keywords: zope3 securitytool security
Platform: UNKNOWN
Classifier: Development Status :: 4 - Beta
Classifier: Environment :: Web Environment
Classifier: Intended Audience :: Developers
Classifier: License :: OSI Approved :: Zope Public License
Classifier: Programming Language :: Python
Classifier: Natural Language :: English
Classifier: Operating System :: OS Independent
Classifier: Topic :: Internet :: WWW/HTTP
Classifier: Framework :: Zope3
